MG_Managers/ALPYNE_ENV_AGENTS.py
MG_Managers/AnyLogicRLAgents.py
MG_Managers/ESM_AGENTS.py
MG_Managers/__init__.py
MG_Managers/_A2CRL/ActorCritic.py
MG_Managers/_A2CRL/DRL.py
MG_Managers/_A2CRL/__init__.py
MG_Managers/_A2CRL/main.py
MG_Managers/_A2CRL/main_ESSAC.py
MG_Managers/_DQRL/ActorCritic.py
MG_Managers/_DQRL/DRL.py
MG_Managers/_DQRL/Q_MLP.py
MG_Managers/_DQRL/__init__.py
MG_Managers/_DQRL/main.py
MG_Managers/_DQRL/main_ESS.py
MG_Managers/_PPORL/PPO_TOOLS.py
MG_Managers/_PPORL/__init__.py
MG_Managers/_PPORL/ppo_agent.py
_DATAGENERATORS/_DataGenerators.py
_DATAGENERATORS/__init__.py
_DATAGENERATORS/Demand_Generators/DemandGenerators.py
_DATAGENERATORS/Demand_Generators/__init__.py
_DATAGENERATORS/Demand_Generators/__main__.py
_DATAGENERATORS/PV_Generators/PVGenerators.py
_DATAGENERATORS/PV_Generators/__input__.py
_DATAGENERATORS/PV_Generators/__main__.py
_RLCoach_ENVS/_GRID_ENVs.py
_RLCoach_ENVS/__init__.py
rl_microgrid_managers-0.0.13.dist-info/LICENSE
rl_microgrid_managers-0.0.13.dist-info/METADATA
rl_microgrid_managers-0.0.13.dist-info/WHEEL
rl_microgrid_managers-0.0.13.dist-info/top_level.txt
rl_microgrid_managers-0.0.13.dist-info/RECORD
